{
  "title": "Nord",
  "text": "Nord, a word meaning \"north\" in several European languages, may refer to:\n\n\n== Acronyms ==\nNational Organization for Rare Disorders, an American nonprofit organization\nNew Orleans Recreation Department, New Orleans, Louisiana, US\n\n\n== Film and television ==\nNord (1991 film), a film directed by Xavier Beauvois\nNord (2009 film), or North, a Norwegian film directed by Rune Denstad Langlo\n\n\n== Music ==\nNord (Siddharta album), 2001\nNord (Year of No Light album), 2006\nNord, an album by Luna Amar\u0103, 2018\nNord, an album by Alfa, 2021\nNord, the brand name for electronic keyboards and percussion synthesizers produced by Clavia.\nA. G. NORD, the fifth disc from the album 7G, by A. G. Cook.\nNord (G\u00e5te album), 2021\n\n\n== People ==\nBjorn Nord (born 1972), Swedish ice hockey player\nChristiane Nord (born 1943), German translation scholar\nDaniel Nord, Swedish civil servant\nElizabeth Nord (1902\u20131986), American labor organizer\nHaavard Nord, Norwegian software expert\nJohn Nord (born 1959), American professional wrestler\nKarl Nord (1912\u20132003), German anti-Nazi activist\nKathleen Nord (born 1965), German swimmer\nKeith Nord (born 1957), American football player\nOle Tom Nord (born 1940), Norwegian skier\nOrla Nord (1875\u2013?), Danish cyclist\nPierre Nord (1900\u20131985), French writer and spy\nRichard Nord, film editor\nThomas Nord (born 1957), German politician (Die Linke)\nWalter R. Nord (born 1939), American academic\n\n\n== Places ==\nNord (Chamber of Deputies of Luxembourg constituency), an electoral constituency\nNord (French department)\nNord (Haitian department)\nNord, California, US, an unincorporated community\nNord, Greenland, a military and scientific base\nNord Region (Burkina Faso)\nNord Region (Cameroon)\n\n\n== Transportation ==\nNord (yacht), a German superyacht\nNord Aviation, a former state-owned French aircraft manufacturer\nChemins de fer du Nord, or the Nord company, a French railway company\nNord Automobiles aka Nord Motion, a Nigerian automaker\n\n\n== Other uses ==\nNord University, a public university in Norway\nNORD (ice hockey team), a defunct Ukrainian amateur team\nNord (novel), published in English as North, a 1960 novel by Louis-Ferdinand C\u00e9line\nNord (video game), a 2009 Facebook video game\n12501 Nord, an asteroid\n6th SS Mountain Division Nord, a WaffenSS division in World War II\nOnePlus Nord, a smartphone 5G by OnePlus\nNords, a fictional race in the Elder Scrolls fantasy setting\nNord Pool, a pan-European electric power exchange\nNordVPN, a VPN service\n\n\n== See also ==\nGare du Nord (disambiguation)\nNorth (disambiguation)\nNorte (disambiguation), Spanish, Portuguese and Galician for north\nAll pages with titles beginning with Nord \nAll pages with titles containing Nord",
  "source_url": "https://en.wikipedia.org/wiki/Nord",
  "fetched_at": "2025-12-06T07:25:59.087298",
  "page_id": "3999168"
}