{
  "metadata": {
    "type": "EGOSCHEMA_PREDICTIONS",
    "source": "100% END\u00d3GENO",
    "timestamp": {
      "value": "2025-12-08T14:44:21.641171",
      "origin": "datetime.now()",
      "source": "FROM_DATA"
    },
    "model": {
      "value": "NEO_EVA_PSILA",
      "origin": "project_model",
      "source": "FROM_DATA"
    },
    "psi_score": {
      "value": 0.5501,
      "origin": "psila_log.psi.benchmark_value",
      "source": "FROM_DATA"
    }
  },
  "format": {
    "value": "question_id -> answer_index",
    "origin": "egoschema_submission_format",
    "source": "FROM_DATA"
  },
  "predictions": {},
  "n_predictions": {
    "value": 0,
    "origin": "len(predictions)",
    "source": "FROM_MATH"
  },
  "submission_ready": {
    "value": false,
    "origin": "needs_real_model_inference",
    "source": "FROM_DATA"
  }
}